retemplar/__init__.py
retemplar/cli.py
retemplar/constants.py
retemplar/core.py
retemplar/lockfile.py
retemplar/logging.py
retemplar/schema.py
retemplar/template_processor.py
retemplar/engines/__init__.py
retemplar/engines/cookiecutter_engine.py
retemplar/engines/jinja_engine.py
retemplar/engines/null_engine.py
retemplar/engines/raw_str_replace.py
retemplar/engines/regex_replace.py
retemplar/engines/registry.py
retemplar/utils/__init__.py
retemplar/utils/apply_utils.py
retemplar/utils/blockprotect.py
retemplar/utils/fs_utils.py
retemplar/utils/merge_utils.py
retemplar/utils/plan_utils.py
retemplar-0.0.0a5.dist-info/METADATA
retemplar-0.0.0a5.dist-info/WHEEL
retemplar-0.0.0a5.dist-info/entry_points.txt
retemplar-0.0.0a5.dist-info/licenses/LICENSE
retemplar-0.0.0a5.dist-info/RECORD
