Metadata-Version: 2.4
Name: retemplar
Version: 0.0.0a5
Summary: Repo-as-Template (RAT) engine with lockfile and incremental upgrades.
Author: Harrison
License-File: LICENSE
Requires-Python: >=3.12
Requires-Dist: cookiecutter>=2.6.0
Requires-Dist: jinja2>=3.1.6
Requires-Dist: pathspec>=0.12.1
Requires-Dist: pydantic>=2.5.0
Requires-Dist: pyyaml>=6.0.1
Requires-Dist: rich>=13.7.1
Requires-Dist: structlog>=25.4.0
Requires-Dist: typer>=0.12.3
